Mensajes/__init__.py
Mensajes/Adios/__init__.py
Mensajes/Adios/despedidas.py
Mensajes/Hola/__init__.py
Mensajes/Hola/saludos.py
tests/__init__.py
tests/test_hola.py
Mensajes_JMarroquin-4.0.dist-info/LICENSE
Mensajes_JMarroquin-4.0.dist-info/METADATA
Mensajes_JMarroquin-4.0.dist-info/WHEEL
Mensajes_JMarroquin-4.0.dist-info/top_level.txt
Mensajes_JMarroquin-4.0.dist-info/RECORD
