Metadata-Version: 2.1
Name: Mensajes-JMarroquin
Version: 4.0
Summary: Un paquete para saludar y despedir
Home-page: https://www.instagram.com/j_marrokings/
Author: Jesús Marroquín
Author-email: jesusmarro12reyes@gmail.com
Classifier: Development Status :: 4 - Beta
Classifier: Environment :: Console
Classifier: Intended Audience :: Developers
Classifier: License :: OSI Approved :: MIT License
Classifier: Operating System :: OS Independent
Classifier: Programming Language :: Python
Classifier: Programming Language :: Python :: 3.10
Classifier: Topic :: Utilities
License-File: LICENSE
Requires-Dist: numpy
